wcs/samlauth/__init__.py
wcs/samlauth/configure.zcml
wcs/samlauth/default_settings.py
wcs/samlauth/forms.py
wcs/samlauth/interfaces.py
wcs/samlauth/plugin.py
wcs/samlauth/testing.py
wcs/samlauth/user_properties.py
wcs/samlauth/utils.py
wcs/samlauth/views.py
wcs/samlauth/templates/add_plugin.zpt
wcs/samlauth/templates/config.zpt
wcs/samlauth/templates/load_idp_metadata_form.pt
wcs/samlauth/tests/__init__.py
wcs/samlauth/tests/test_fetch_idp_metadata.py
wcs/samlauth/tests/test_idp_config_variants.py
wcs/samlauth/tests/test_layer.py
wcs/samlauth/tests/test_login.py
wcs/samlauth/tests/test_logout.py
wcs/samlauth/tests/test_sp_config_variants.py
wcs/samlauth/tests/test_sp_metadata.py
wcs/samlauth/tests/user_property_adapters.py
wcs/samlauth/tests/assets/saml-test-realm-custom-attr.json
wcs/samlauth/tests/assets/saml-test-realm-sp-signature-metadata.json
wcs/samlauth/tests/assets/saml-test-realm-sp-signature.json
wcs/samlauth/tests/assets/saml-test-realm.json
wcs/samlauth/tests/assets/sp.cer
wcs/samlauth/tests/assets/sp.csr
wcs/samlauth/tests/assets/sp_private_key
wcs_samlauth-1.3.0.dist-info/METADATA
wcs_samlauth-1.3.0.dist-info/WHEEL
wcs_samlauth-1.3.0.dist-info/entry_points.txt
wcs_samlauth-1.3.0.dist-info/top_level.txt
wcs_samlauth-1.3.0.dist-info/RECORD
