Metadata-Version: 2.4
Name: wcs.samlauth
Version: 1.3.0
Summary: SAML authentication for plone sites
Home-page: https://pypi.python.org/pypi/wcs.samlauth
Author: Mathias Leimgruber
Author-email: m.leimgruber@webcloud7.ch
License: GPL version 2
Project-URL: PyPI, https://pypi.python.org/pypi/wcs.samlauth
Project-URL: Source, https://github.com/webcloud7/wcs.samlauth
Project-URL: Tracker, https://github.com/webcloud7/wcs.samlauth/issues
Project-URL: Documentation, https://github.com/webcloud7/wcs.samlauth/blob/main/README.md
Keywords: Plone Authentication SAML
Classifier: Environment :: Web Environment
Classifier: Framework :: Plone
Classifier: Framework :: Plone :: 6.0
Classifier: Framework :: Plone :: 6.1
Classifier: Framework :: Plone :: Addon
Classifier: Programming Language :: Python
Classifier: Programming Language :: Python :: 3.11
Classifier: Programming Language :: Python :: 3.12
Classifier: Development Status :: 5 - Production/Stable
Requires-Dist: python3-saml
Requires-Dist: Plone
Requires-Dist: plone.autoinclude
Requires-Dist: plone.restapi
Requires-Dist: setuptools
Provides-Extra: test
Requires-Dist: plone.app.testing; extra == "test"
Requires-Dist: plone.testing; extra == "test"
Requires-Dist: plone.api; extra == "test"
Requires-Dist: zope.testrunner; extra == "test"
Requires-Dist: requests; extra == "test"
Requires-Dist: beautifulsoup4; extra == "test"
Provides-Extra: tests
Requires-Dist: plone.app.testing; extra == "tests"
Requires-Dist: plone.testing; extra == "tests"
Requires-Dist: plone.api; extra == "tests"
Requires-Dist: zope.testrunner; extra == "tests"
Requires-Dist: requests; extra == "tests"
Requires-Dist: beautifulsoup4; extra == "tests"
Dynamic: author
Dynamic: author-email
Dynamic: classifier
Dynamic: description
Dynamic: description-content-type
Dynamic: home-page
Dynamic: keywords
Dynamic: license
Dynamic: project-url
Dynamic: provides-extra
Dynamic: requires-dist
Dynamic: summary
